priyam/__init__.py
priyam/apps.py
priyam/chemistry.py
priyam/cs.py
priyam/latex_support.py
priyam/physics.py
priyam/pmath.py
priyam/string_utils.py
priyam/external/LinkCheckerOriginal.py
priyam/external/notepadOriginal.py
priyam/external/slideExtractorApp.py
priyam/external/slide_extractor.py
priyam-0.0.1.dist-info/LICENSE
priyam-0.0.1.dist-info/METADATA
priyam-0.0.1.dist-info/WHEEL
priyam-0.0.1.dist-info/top_level.txt
priyam-0.0.1.dist-info/RECORD
