Metadata-Version: 2.1
Name: priyam
Version: 0.0.1
Summary: Comprehensive Python suite: Math, Physics, Chemistry, Computer Science, Algorithms, String & LaTeX utilities, GUI tools (link checker, notepad, slide extractor)
Home-page: https://github.com/shreyazh/priyam
Author: justshreyash
Author-email: The Priyam Team <usershreyash@gmail.com>
Maintainer-email: The Priyam Team <usershreyash@gmail.com>
License: GNU GENERAL PUBLIC LICENSE
Project-URL: Homepage, https://priyam-python.vercel.app
Project-URL: Documentation, https://github.com/shreyazh/priyam/docs
Project-URL: Repository, https://github.com/shreyazh/priyam
Project-URL: Issues, https://github.com/shreyazh/priyam/issues
Keywords: math,utilities,statistics,algebra,number-theory,science,physics,chemistry,computer-science,algorithms,graphs,string,latex,desktop-app,linkchecker,notepad,slide-extractor,ocr
Classifier: Development Status :: 5 - Production/Stable
Classifier: Intended Audience :: Education
Classifier: Intended Audience :: Science/Research
Classifier: Intended Audience :: Developers
Classifier: License :: OSI Approved :: MIT License
Classifier: Operating System :: OS Independent
Classifier: Programming Language :: Python :: 3
Classifier: Programming Language :: Python :: 3.7
Classifier: Programming Language :: Python :: 3.8
Classifier: Programming Language :: Python :: 3.9
Classifier: Programming Language :: Python :: 3.10
Classifier: Topic :: Education
Classifier: Topic :: Scientific/Engineering :: Mathematics
Classifier: Topic :: Scientific/Engineering :: Physics
Classifier: Topic :: Scientific/Engineering :: Chemistry
Classifier: Topic :: Software Development :: Libraries :: Python Modules
Classifier: Topic :: Utilities
Classifier: Topic :: Software Development :: User Interfaces
Requires-Python: >=3.7
License-File: LICENSE
Requires-Dist: pytz>=2021.3
Requires-Dist: python-dateutil>=2.8.2
Requires-Dist: sympy>=1.9
Provides-Extra: dev
Requires-Dist: pytest>=6.0; extra == "dev"
Requires-Dist: pytest-cov>=2.0; extra == "dev"
Requires-Dist: black>=21.0; extra == "dev"
Requires-Dist: flake8>=3.9; extra == "dev"
Requires-Dist: sphinx>=4.0; extra == "dev"
Requires-Dist: sphinx-rtd-theme>=1.0; extra == "dev"
Requires-Dist: requests; extra == "dev"
Requires-Dist: beautifulsoup4; extra == "dev"
Requires-Dist: playwright; extra == "dev"
Requires-Dist: lxml; extra == "dev"
Requires-Dist: opencv-python; extra == "dev"
Requires-Dist: pytesseract; extra == "dev"
Requires-Dist: Pillow; extra == "dev"
Requires-Dist: yt-dlp; extra == "dev"
Requires-Dist: scikit-image; extra == "dev"
Requires-Dist: tk; extra == "dev"
Requires-Dist: reportlab; extra == "dev"
